{
	"$schema": "https://schemas.wp.org/trunk/block.json",
	"apiVersion": 3,
	"name": "data-tables/data-filter-donation-year",
	"version": "0.1.0",
	"title": "Data Filter - Year",
	"description": "Display donation year filter.",
	"category": "widgets",
	"icon": "calendar-alt",
	"attributes": {
		"donationYear": {
			"type": "string"
		},
		"defaultDonationYear": {
			"type": "string"
		}
	},
	"example": {},
	"supports": {
		"interactivity": true,
		"customClassName": true,
		"renaming": true
	},
	"providesContext": {
		"data-tables/donation-year": "donationYear"
	},
	"textdomain": "data-tables",
	"editorScript": "file:./index.js",
	"editorStyle": "file:./index.css",
	"style": "file:./style-index.css",
	"render": "file:./render.php",
	"viewScriptModule": "file:./view.js"
}
